perftrack/__init__.py
perftrack/cli.py
perftrack/compare.py
perftrack/report.py
perftrack/sampler.py
perftrack-0.1.1.dist-info/licenses/LICENSE
perftrack-0.1.1.dist-info/METADATA
perftrack-0.1.1.dist-info/WHEEL
perftrack-0.1.1.dist-info/entry_points.txt
perftrack-0.1.1.dist-info/top_level.txt
perftrack-0.1.1.dist-info/RECORD
