Metadata-Version: 2.4
Name: perftrack
Version: 0.1.1
Summary: Lightweight CLI tool to detect performance regressions by comparing local benchmark snapshots.
Author-email: Pravin <p-r-a-v-i-n@users.noreply.github.com>
License-Expression: MIT
Project-URL: Homepage, https://github.com/p-r-a-v-i-n/perftrack
Project-URL: Issues, https://github.com/p-r-a-v-i-n/perftrack/issues
Keywords: benchmark,cli,performance,regression
Classifier: Intended Audience :: Developers
Classifier: Operating System :: OS Independent
Classifier: Programming Language :: Python :: 3 :: Only
Classifier: Programming Language :: Python :: 3.9
Classifier: Programming Language :: Python :: 3.10
Classifier: Programming Language :: Python :: 3.11
Classifier: Programming Language :: Python :: 3.12
Classifier: Programming Language :: Python :: 3.13
Classifier: Programming Language :: Python :: 3.14
Requires-Python: >=3.9
License-File: LICENSE
Requires-Dist: psutil<8,>=7.1.3
Provides-Extra: dev
Requires-Dist: pre-commit; extra == "dev"
Requires-Dist: pytest; extra == "dev"
Requires-Dist: pytest-cov; extra == "dev"
Requires-Dist: ruff; extra == "dev"
Dynamic: license-file
